setup.py
lh_clean_tool/__init__.py
lh_clean_tool/universal_utils.py
lh_clean_tool/utils.py
lh_clean_tool/ymysql.py
lh_clean_tool.egg-info/PKG-INFO
lh_clean_tool.egg-info/SOURCES.txt
lh_clean_tool.egg-info/dependency_links.txt
lh_clean_tool.egg-info/top_level.txt